tigerhash.cpython-39-darwin.so
tigerhash-0.2.0.dist-info/LICENSE
tigerhash-0.2.0.dist-info/METADATA
tigerhash-0.2.0.dist-info/WHEEL
tigerhash-0.2.0.dist-info/top_level.txt
tigerhash-0.2.0.dist-info/RECORD
