Metadata-Version: 2.1
Name: tigerhash
Version: 0.2.0
Summary: Implementation of tiger hash in C++ with Python API. 
Home-page: https://github.com/Badcat330/TigerHash
Author: Alex Glushko
Author-email: aglushko@hse.ru
License: UNKNOWN
Platform: UNKNOWN
Classifier: Programming Language :: Cython
Classifier: License :: OSI Approved :: Apache Software License
Classifier: Operating System :: OS Independent
Classifier: Development Status :: 1 - Planning
Requires-Python: >=3.9
Requires-Dist: cython
